[{"0": 1, "1": 1, "2": 1, "3": 1, "4": 1, "5": 0, "6": 0, "7": 1, "8": 1, "9": 1, "etm_scenario": "high_demand", "scenario_id": 1668766, "co2": -0.44130882713856556, "import_dependency": 0.6846197841465796, "costs": 60.25944404051822, "unused_heat": 0.0, "geothermal_heat": 0.0, "industrial_heat": 0.0}, {"0": 1, "1": 1, "2": 1, "3": 1, "4": 1, "5": 0, "6": 0, "7": 1, "8": 1, "9": 1, "etm_scenario": "medium_demand", "scenario_id": 1668767, "co2": -0.5124078926485013, "import_dependency": 0.659859783712973, "costs": 54.36199099175515, "unused_heat": 0.0, "geothermal_heat": 0.0, "industrial_heat": 0.0}, {"0": 1, "1": 1, "2": 1, "3": 1, "4": 1, "5": 0, "6": 0, "7": 1, "8": 1, "9": 1, "etm_scenario": "low_demand", "scenario_id": 1668768, "co2": -0.5655197117223019, "import_dependency": 0.6292063976730653, "costs": 52.05959810755571, "unused_heat": 0.0, "geothermal_heat": 0.0, "industrial_heat": 0.0}]